flexplan-0.0.2.dist-info/METADATA
flexplan-0.0.2.dist-info/WHEEL
flexplan-0.0.2.dist-info/licenses/LICENSE
flexplan/__init__.py
flexplan/datastructures/__init__.py
flexplan/datastructures/deferredbox.py
flexplan/datastructures/future.py
flexplan/datastructures/instancecreator.py
flexplan/datastructures/types.py
flexplan/errors.py
flexplan/messages/__init__.py
flexplan/messages/mail.py
flexplan/messages/message.py
flexplan/stations/__init__.py
flexplan/stations/base.py
flexplan/stations/local.py
flexplan/stations/mixins.py
flexplan/stations/process.py
flexplan/stations/thread.py
flexplan/supervisor.py
flexplan/types.py
flexplan/utils/__init__.py
flexplan/utils/identity.py
flexplan/utils/inspect.py
flexplan/utils/pickle.py
flexplan/workbench/__init__.py
flexplan/workbench/base.py
flexplan/workbench/loop.py
flexplan/workbench/simple.py
flexplan/workers/__init__.py
flexplan/workers/base.py
flexplan/workshop.py
flexplan-0.0.2.dist-info/RECORD
